[
  {
    "attribute": "children",
    "type": "ReactNode",
    "description": "The content of the code.",
    "default": "-"
  },
  {
    "attribute": "size",
    "type": "sm | md | lg",
    "description": "The size of the code.",
    "default": "sm"
  },
  {
    "attribute": "color",
    "type": "default | primary | secondary | success | warning | danger",
    "description": "The color of the code.",
    "default": "default"
  },
  {
    "attribute": "radius",
    "type": "none | sm | md | lg | full",
    "description": "The radius of the code.",
    "default": "sm"
  }
]